wLpylib/__init__.py
wLpylib/exporter/__init__.py
wLpylib/exporter/exceptions.py
wLpylib/exporter/exportconfig.py
wLpylib/parser/__init__.py
wLpylib/parser/exceptions.py
wlpylib-1.3.3.dist-info/METADATA
wlpylib-1.3.3.dist-info/WHEEL
wlpylib-1.3.3.dist-info/RECORD
