Metadata-Version: 2.4
Name: wLpylib
Version: 1.3.3
Summary: wL support package for python
Project-URL: Homepage, https://github.com/wilhelmbismarck/wL
Project-URL: Issues, https://github.com/wilhelmbismarck/wL/issues
Author-email: wilhelm43 <wilhelmbismarck@tutanota.de>
Classifier: Operating System :: OS Independent
Classifier: Programming Language :: Python :: 3
Requires-Python: >=3.9
